.pypi_readme.md
MANIFEST.in
README.md
setup.py
kusp/__init__.py
kusp/__version__.py
kusp/install_kim_model.py
kusp/server.py
kusp/socket_serve.py
kusp.egg-info/PKG-INFO
kusp.egg-info/SOURCES.txt
kusp.egg-info/dependency_links.txt
kusp.egg-info/requires.txt
kusp.egg-info/top_level.txt
kusp/KUSP__MO_000000000000_000/CMakeLists.txt
kusp/KUSP__MO_000000000000_000/KUSPPortableModel.cpp
kusp/KUSP__MO_000000000000_000/KUSPPortableModel.hpp
kusp/KUSP__MO_000000000000_000/README.md
kusp/KUSP__MO_000000000000_000/kimspec.edn
kusp/KUSP__MO_000000000000_000/yaml-cpp/CMakeLists.txt
kusp/KUSP__MO_000000000000_000/yaml-cpp/CONTRIBUTING.md
kusp/KUSP__MO_000000000000_000/yaml-cpp/LICENSE
kusp/KUSP__MO_000000000000_000/yaml-cpp/README.md
kusp/KUSP__MO_000000000000_000/yaml-cpp/SECURITY.md
kusp/KUSP__MO_000000000000_000/yaml-cpp/cmake_uninstall.cmake.in
kusp/KUSP__MO_000000000000_000/yaml-cpp/install.txt
kusp/KUSP__MO_000000000000_000/yaml-cpp/yaml-cpp-config.cmake.in
kusp/KUSP__MO_000000000000_000/yaml-cpp/yaml-cpp.pc.in
kusp/KUSP__MO_000000000000_000/yaml-cpp/include/yaml-cpp/anchor.h
kusp/KUSP__MO_000000000000_000/yaml-cpp/include/yaml-cpp/binary.h
kusp/KUSP__MO_000000000000_000/yaml-cpp/include/yaml-cpp/depthguard.h
kusp/KUSP__MO_000000000000_000/yaml-cpp/include/yaml-cpp/dll.h
kusp/KUSP__MO_000000000000_000/yaml-cpp/include/yaml-cpp/emitfromevents.h
kusp/KUSP__MO_000000000000_000/yaml-cpp/include/yaml-cpp/emitter.h
kusp/KUSP__MO_000000000000_000/yaml-cpp/include/yaml-cpp/emitterdef.h
kusp/KUSP__MO_000000000000_000/yaml-cpp/include/yaml-cpp/emittermanip.h
kusp/KUSP__MO_000000000000_000/yaml-cpp/include/yaml-cpp/emitterstyle.h
kusp/KUSP__MO_000000000000_000/yaml-cpp/include/yaml-cpp/eventhandler.h
kusp/KUSP__MO_000000000000_000/yaml-cpp/include/yaml-cpp/exceptions.h
kusp/KUSP__MO_000000000000_000/yaml-cpp/include/yaml-cpp/mark.h
kusp/KUSP__MO_000000000000_000/yaml-cpp/include/yaml-cpp/noexcept.h
kusp/KUSP__MO_000000000000_000/yaml-cpp/include/yaml-cpp/null.h
kusp/KUSP__MO_000000000000_000/yaml-cpp/include/yaml-cpp/ostream_wrapper.h
kusp/KUSP__MO_000000000000_000/yaml-cpp/include/yaml-cpp/parser.h
