Metadata-Version: 2.1
Name: kusp
Version: 0.1.0
Summary: kusp: KIM Utility for Serving Potentials
Author: Amit Gupta
Author-email: gupta839@umn.edu
